{
  "entrypoints": [
    "main"
  ],
  "origins": {
    "0": [
      1,
      2,
      6,
      7,
      8,
      9,
      10,
      11,
      12,
      146,
      0
    ],
    "1": [
      0,
      2,
      6,
      7,
      8,
      9,
      10,
      12,
      146,
      1
    ],
    "2": [
      0,
      1,
      7,
      8,
      10,
      12,
      2
    ],
    "3": [
      48,
      63,
      3
    ],
    "C:\\Users\\LG\\GitHub\\loader-manual\\src\\pages\\home\\features.js": [
      0,
      1,
      6
    ],
    "C:\\Users\\LG\\GitHub\\loader-manual\\src\\pages\\home\\header.js": [
      0,
      1,
      6
    ],
    "C:\\Users\\LG\\GitHub\\loader-manual\\src\\pages\\index.js": [
      0,
      1,
      6
    ],
    "@theme/BlogListPage": [
      0,
      1,
      2,
      7
    ],
    "@theme/BlogPostPage": [
      0,
      1,
      2,
      8
    ],
    "@theme/BlogTagsListPage": [
      0,
      1,
      9
    ],
    "@theme/BlogTagsPostsPage": [
      0,
      1,
      2,
      10
    ],
    "@theme/DocLegacyItem": [
      0,
      11
    ],
    "@theme/DocLegacyPage": [
      0,
      1,
      2,
      12
    ],
    "C:\\Users\\LG\\GitHub\\loader-manual\\blog\\2025-08-25-release-1.2.0.md?truncated=true": [
      13
    ],
    "C:\\Users\\LG\\GitHub\\loader-manual\\blog\\2022-11-16-release-1.1.21.md?truncated=true": [
      14
    ],
    "C:\\Users\\LG\\GitHub\\loader-manual\\blog\\2025-11-29-release-1.3.3.md?truncated=true": [
      15
    ],
    "C:\\Users\\LG\\GitHub\\loader-manual\\blog\\2023-08-10-release-1.1.22.md?truncated=true": [
      16
    ],
    "C:\\Users\\LG\\GitHub\\loader-manual\\blog\\2025-11-28-release-1.3.2.md?truncated=true": [
      17
    ],
    "C:\\Users\\LG\\GitHub\\loader-manual\\blog\\2024-08-19-release-1.1.25.md?truncated=true": [
      18
    ],
    "C:\\Users\\LG\\GitHub\\loader-manual\\blog\\2025-11-26-release-1.3.0.md?truncated=true": [
      19
    ],
    "C:\\Users\\LG\\GitHub\\loader-manual\\blog\\2025-11-27-release-1.3.1.md?truncated=true": [
      20
    ],
    "C:\\Users\\LG\\GitHub\\loader-manual\\blog\\2024-05-10-release-1.1.24.md?truncated=true": [
      21
    ],
    "C:\\Users\\LG\\GitHub\\loader-manual\\blog\\2023-11-27-release-1.1.23.md?truncated=true": [
      22
    ],
    "C:\\Users\\LG\\GitHub\\loader-manual\\blog\\2022-03-08-release-1.1.14.md?truncated=true": [
      23
    ],
    "C:\\Users\\LG\\GitHub\\loader-manual\\blog\\2022-07-08-release-1.1.16.md?truncated=true": [
      24
    ],
    "C:\\Users\\LG\\GitHub\\loader-manual\\blog\\2022-07-08-release-1.1.18.md?truncated=true": [
      25
    ],
    "C:\\Users\\LG\\GitHub\\loader-manual\\blog\\2022-06-13-release-1.1.15.md?truncated=true": [
      26
    ],
    "C:\\Users\\LG\\GitHub\\loader-manual\\blog\\2019-09-30-release-0.0.9.md?truncated=true": [
      27
    ],
    "C:\\Users\\LG\\GitHub\\loader-manual\\blog\\2022-08-23-release-1.1.19.md?truncated=true": [
      28
    ],
    "C:\\Users\\LG\\GitHub\\loader-manual\\blog\\2019-09-30-release-0.0.9.md": [
      29
    ],
    "C:\\Users\\LG\\GitHub\\loader-manual\\blog\\2022-03-08-release-1.1.14.md": [
      30
    ],
    "C:\\Users\\LG\\GitHub\\loader-manual\\blog\\2022-06-13-release-1.1.15.md": [
      31
    ],
    "C:\\Users\\LG\\GitHub\\loader-manual\\blog\\2022-07-08-release-1.1.16.md": [
      32
    ],
    "C:\\Users\\LG\\GitHub\\loader-manual\\blog\\2022-07-08-release-1.1.18.md": [
      33
    ],
    "C:\\Users\\LG\\GitHub\\loader-manual\\blog\\2022-08-23-release-1.1.19.md": [
      34
    ],
    "C:\\Users\\LG\\GitHub\\loader-manual\\blog\\2022-11-16-release-1.1.21.md": [
      35
    ],
    "C:\\Users\\LG\\GitHub\\loader-manual\\blog\\2023-08-10-release-1.1.22.md": [
      36
    ],
    "C:\\Users\\LG\\GitHub\\loader-manual\\blog\\2023-11-27-release-1.1.23.md": [
      37
    ],
    "C:\\Users\\LG\\GitHub\\loader-manual\\blog\\2024-05-10-release-1.1.24.md": [
      38
    ],
    "C:\\Users\\LG\\GitHub\\loader-manual\\blog\\2024-08-19-release-1.1.25.md": [
      39
    ],
    "C:\\Users\\LG\\GitHub\\loader-manual\\blog\\2025-08-25-release-1.2.0.md": [
      40
    ],
    "C:\\Users\\LG\\GitHub\\loader-manual\\blog\\2025-11-26-release-1.3.0.md": [
      41
    ],
    "C:\\Users\\LG\\GitHub\\loader-manual\\blog\\2025-11-27-release-1.3.1.md": [
      42
    ],
    "C:\\Users\\LG\\GitHub\\loader-manual\\blog\\2025-11-28-release-1.3.2.md": [
      43
    ],
    "C:\\Users\\LG\\GitHub\\loader-manual\\blog\\2025-11-29-release-1.3.3.md": [
      44
    ],
    "C:\\Users\\LG\\GitHub\\loader-manual\\docs\\adv\\config.md": [
      45
    ],
    "C:\\Users\\LG\\GitHub\\loader-manual\\docs\\adv\\events.md": [
      46
    ],
    "C:\\Users\\LG\\GitHub\\loader-manual\\docs\\adv\\load.md": [
      47
    ],
    "C:\\Users\\LG\\GitHub\\loader-manual\\docs\\adv\\registry.md": [
      3,
      48
    ],
    "C:\\Users\\LG\\GitHub\\loader-manual\\docs\\adv\\unload.md": [
      49
    ],
    "C:\\Users\\LG\\GitHub\\loader-manual\\docs\\basic\\getting-started.md": [
      50
    ],
    "C:\\Users\\LG\\GitHub\\loader-manual\\docs\\demo\\angular-demo.md": [
      51
    ],
    "C:\\Users\\LG\\GitHub\\loader-manual\\docs\\demoIBChart\\angular-demo.md": [
      52
    ],
    "C:\\Users\\LG\\GitHub\\loader-manual\\docs\\demoIBChart\\react-demo.md": [
      53
    ],
    "C:\\Users\\LG\\GitHub\\loader-manual\\docs\\demoIBChart\\vue-demo.md": [
      54
    ],
    "C:\\Users\\LG\\GitHub\\loader-manual\\docs\\demoIBMap\\angular-demo.md": [
      55
    ],
    "C:\\Users\\LG\\GitHub\\loader-manual\\docs\\demoIBMap\\react-demo.md": [
      56
    ],
    "C:\\Users\\LG\\GitHub\\loader-manual\\docs\\demoIBMap\\vue-demo.md": [
      57
    ],
    "C:\\Users\\LG\\GitHub\\loader-manual\\docs\\demo\\react-demo.md": [
      58
    ],
    "C:\\Users\\LG\\GitHub\\loader-manual\\docs\\demo\\vue-demo.md": [
      59
    ],
    "C:\\Users\\LG\\GitHub\\loader-manual\\docs\\etc\\external-lib.md": [
      60
    ],
    "C:\\Users\\LG\\GitHub\\loader-manual\\docs\\etc\\load-flow.md": [
      61
    ],
    "C:\\Users\\LG\\GitHub\\loader-manual\\docs\\etc\\start-package.md": [
      62
    ],
    "C:\\Users\\LG\\GitHub\\loader-manual\\docs\\etc\\trouble-shooting.md": [
      3,
      63
    ],
    "C:\\Users\\LG\\GitHub\\loader-manual\\docs\\ibchart\\create-chart.md": [
      64
    ],
    "C:\\Users\\LG\\GitHub\\loader-manual\\docs\\ibchart\\remove-chart.md": [
      65
    ],
    "C:\\Users\\LG\\GitHub\\loader-manual\\docs\\ibmap\\create-map.md": [
      66
    ],
    "C:\\Users\\LG\\GitHub\\loader-manual\\docs\\ibmap\\remove-map.md": [
      67
    ],
    "C:\\Users\\LG\\GitHub\\loader-manual\\docs\\ibsheet\\create-sheet.md": [
      68
    ],
    "C:\\Users\\LG\\GitHub\\loader-manual\\docs\\ibsheet\\remove-sheet.md": [
      69
    ],
    "C:\\Users\\LG\\GitHub\\loader-manual\\docs\\spa\\angular.md": [
      70
    ],
    "C:\\Users\\LG\\GitHub\\loader-manual\\docs\\spa\\react.md": [
      71
    ],
    "C:\\Users\\LG\\GitHub\\loader-manual\\docs\\spa\\vue.md": [
      72
    ],
    "C:\\Users\\LG\\GitHub\\loader-manual\\.docusaurus\\docusaurus-plugin-content-docs\\loader-manual-docs-add.json": [
      73
    ],
    "main": [
      143,
      74
    ],
    "C:\\Users\\LG\\GitHub\\loader-manual\\.docusaurus\\docusaurus-plugin-content-pages\\loader-manual-401.json": [
      75
    ],
    "C:\\Users\\LG\\GitHub\\loader-manual\\.docusaurus\\docusaurus-plugin-content-blog\\loader-manual-blog-68d.json": [
      76
    ],
    "C:\\Users\\LG\\GitHub\\loader-manual\\.docusaurus\\docusaurus-plugin-content-blog\\loader-manual-blog-page-2-333.json": [
      77
    ],
    "C:\\Users\\LG\\GitHub\\loader-manual\\.docusaurus\\docusaurus-plugin-content-blog\\loader-manual-blog-release-1-3-3-d1c.json": [
      78
    ],
    "C:\\Users\\LG\\GitHub\\loader-manual\\.docusaurus\\docusaurus-plugin-content-blog\\loader-manual-blog-tags-ibsheet-loader-636.json": [
      79
    ],
    "C:\\Users\\LG\\GitHub\\loader-manual\\.docusaurus\\docusaurus-plugin-content-blog\\loader-manual-blog-tags-npm-db8.json": [
      80
    ],
    "C:\\Users\\LG\\GitHub\\loader-manual\\.docusaurus\\docusaurus-plugin-content-blog\\loader-manual-blog-tags-release-4c7.json": [
      81
    ],
    "C:\\Users\\LG\\GitHub\\loader-manual\\.docusaurus\\docusaurus-plugin-content-blog\\loader-manual-blog-tags-v-0-0-9-f64.json": [
      82
    ],
    "C:\\Users\\LG\\GitHub\\loader-manual\\.docusaurus\\docusaurus-plugin-content-blog\\loader-manual-blog-tags-v-1-1-14-ba5.json": [
      83
    ],
    "C:\\Users\\LG\\GitHub\\loader-manual\\.docusaurus\\docusaurus-plugin-content-blog\\loader-manual-blog-tags-v-1-1-15-4c6.json": [
      84
    ],
    "C:\\Users\\LG\\GitHub\\loader-manual\\.docusaurus\\docusaurus-plugin-content-blog\\loader-manual-blog-tags-v-1-1-16-319.json": [
      85
    ],
    "C:\\Users\\LG\\GitHub\\loader-manual\\.docusaurus\\docusaurus-plugin-content-blog\\loader-manual-blog-tags-v-1-1-18-67d.json": [
      86
    ],
    "C:\\Users\\LG\\GitHub\\loader-manual\\.docusaurus\\docusaurus-plugin-content-blog\\loader-manual-blog-tags-v-1-1-19-a98.json": [
      87
    ],
    "C:\\Users\\LG\\GitHub\\loader-manual\\.docusaurus\\docusaurus-plugin-content-blog\\loader-manual-blog-tags-v-1-1-21-984.json": [
      88
    ],
    "C:\\Users\\LG\\GitHub\\loader-manual\\.docusaurus\\docusaurus-plugin-content-blog\\loader-manual-blog-tags-v-1-1-22-2b1.json": [
      89
    ],
    "C:\\Users\\LG\\GitHub\\loader-manual\\.docusaurus\\docusaurus-plugin-content-blog\\loader-manual-blog-tags-v-1-1-23-7c5.json": [
      90
    ],
    "C:\\Users\\LG\\GitHub\\loader-manual\\.docusaurus\\docusaurus-plugin-content-blog\\loader-manual-blog-tags-v-1-1-24-083.json": [
      91
    ],
    "C:\\Users\\LG\\GitHub\\loader-manual\\.docusaurus\\docusaurus-plugin-content-blog\\loader-manual-blog-tags-v-1-1-25-c9e.json": [
      92
    ],
    "C:\\Users\\LG\\GitHub\\loader-manual\\.docusaurus\\docusaurus-plugin-content-blog\\loader-manual-blog-tags-v-1-2-0-6fb.json": [
      93
    ],
    "C:\\Users\\LG\\GitHub\\loader-manual\\.docusaurus\\docusaurus-plugin-content-blog\\loader-manual-blog-tags-v-1-3-0-7bd.json": [
      94
    ],
    "C:\\Users\\LG\\GitHub\\loader-manual\\.docusaurus\\docusaurus-plugin-content-blog\\loader-manual-blog-tags-v-1-3-1-cb1.json": [
      95
    ],
    "C:\\Users\\LG\\GitHub\\loader-manual\\.docusaurus\\docusaurus-plugin-content-blog\\loader-manual-blog-tags-v-1-3-2-c75.json": [
      96
    ],
    "C:\\Users\\LG\\GitHub\\loader-manual\\.docusaurus\\docusaurus-plugin-content-blog\\loader-manual-blog-tags-v-1-3-3-2ea.json": [
      97
    ],
    "C:\\Users\\LG\\GitHub\\loader-manual\\.docusaurus\\docusaurus-plugin-content-docs\\loader-manual-docs-adv-config-444.json": [
      98
    ],
    "C:\\Users\\LG\\GitHub\\loader-manual\\.docusaurus\\docusaurus-plugin-content-docs\\loader-manual-docs-adv-events-655.json": [
      99
    ],
    "C:\\Users\\LG\\GitHub\\loader-manual\\.docusaurus\\docusaurus-plugin-content-docs\\loader-manual-docs-adv-load-ee5.json": [
      100
    ],
    "C:\\Users\\LG\\GitHub\\loader-manual\\.docusaurus\\docusaurus-plugin-content-docs\\loader-manual-docs-adv-registry-343.json": [
      101
    ],
    "C:\\Users\\LG\\GitHub\\loader-manual\\.docusaurus\\docusaurus-plugin-content-docs\\loader-manual-docs-adv-unload-0f9.json": [
      102
    ],
    "C:\\Users\\LG\\GitHub\\loader-manual\\.docusaurus\\docusaurus-plugin-content-docs\\loader-manual-docs-basic-getting-started-3f4.json": [
      103
    ],
    "C:\\Users\\LG\\GitHub\\loader-manual\\.docusaurus\\docusaurus-plugin-content-docs\\loader-manual-docs-demo-angular-demo-14d.json": [
      104
    ],
    "C:\\Users\\LG\\GitHub\\loader-manual\\.docusaurus\\docusaurus-plugin-content-docs\\loader-manual-docs-demo-ib-chart-angular-demo-992.json": [
      105
    ],
    "C:\\Users\\LG\\GitHub\\loader-manual\\.docusaurus\\docusaurus-plugin-content-docs\\loader-manual-docs-demo-ib-chart-react-demo-117.json": [
      106
    ],
    "C:\\Users\\LG\\GitHub\\loader-manual\\.docusaurus\\docusaurus-plugin-content-docs\\loader-manual-docs-demo-ib-chart-vue-demo-067.json": [
      107
    ],
    "C:\\Users\\LG\\GitHub\\loader-manual\\.docusaurus\\docusaurus-plugin-content-docs\\loader-manual-docs-demo-ib-map-angular-demo-2c2.json": [
      108
    ],
    "C:\\Users\\LG\\GitHub\\loader-manual\\.docusaurus\\docusaurus-plugin-content-docs\\loader-manual-docs-demo-ib-map-react-demo-090.json": [
      109
    ],
    "C:\\Users\\LG\\GitHub\\loader-manual\\.docusaurus\\docusaurus-plugin-content-docs\\loader-manual-docs-demo-ib-map-vue-demo-6ea.json": [
      110
    ],
    "C:\\Users\\LG\\GitHub\\loader-manual\\.docusaurus\\docusaurus-plugin-content-docs\\loader-manual-docs-demo-react-demo-733.json": [
      111
    ],
    "C:\\Users\\LG\\GitHub\\loader-manual\\.docusaurus\\docusaurus-plugin-content-docs\\loader-manual-docs-demo-vue-demo-f27.json": [
      112
    ],
    "C:\\Users\\LG\\GitHub\\loader-manual\\.docusaurus\\docusaurus-plugin-content-docs\\loader-manual-docs-etc-external-lib-f2c.json": [
      113
    ],
    "C:\\Users\\LG\\GitHub\\loader-manual\\.docusaurus\\docusaurus-plugin-content-docs\\loader-manual-docs-etc-load-flow-d4c.json": [
      114
    ],
    "C:\\Users\\LG\\GitHub\\loader-manual\\.docusaurus\\docusaurus-plugin-content-docs\\loader-manual-docs-etc-starter-packages-36e.json": [
      115
    ],
    "C:\\Users\\LG\\GitHub\\loader-manual\\.docusaurus\\docusaurus-plugin-content-docs\\loader-manual-docs-etc-trouble-shooting-266.json": [
      116
    ],
    "C:\\Users\\LG\\GitHub\\loader-manual\\.docusaurus\\docusaurus-plugin-content-docs\\loader-manual-docs-ibchart-create-chart-c79.json": [
      117
    ],
    "C:\\Users\\LG\\GitHub\\loader-manual\\.docusaurus\\docusaurus-plugin-content-docs\\loader-manual-docs-ibchart-remove-chart-09a.json": [
      118
    ],
    "C:\\Users\\LG\\GitHub\\loader-manual\\.docusaurus\\docusaurus-plugin-content-docs\\loader-manual-docs-ibmap-create-map-f02.json": [
      119
    ],
    "C:\\Users\\LG\\GitHub\\loader-manual\\.docusaurus\\docusaurus-plugin-content-docs\\loader-manual-docs-ibmap-remove-map-ea4.json": [
      120
    ],
    "C:\\Users\\LG\\GitHub\\loader-manual\\.docusaurus\\docusaurus-plugin-content-docs\\loader-manual-docs-ibsheet-create-sheet-160.json": [
      121
    ],
    "C:\\Users\\LG\\GitHub\\loader-manual\\.docusaurus\\docusaurus-plugin-content-docs\\loader-manual-docs-ibsheet-remove-sheet-fb9.json": [
      122
    ],
    "C:\\Users\\LG\\GitHub\\loader-manual\\.docusaurus\\docusaurus-plugin-content-docs\\loader-manual-docs-spa-angular-f9d.json": [
      123
    ],
    "C:\\Users\\LG\\GitHub\\loader-manual\\.docusaurus\\docusaurus-plugin-content-docs\\loader-manual-docs-spa-react-e93.json": [
      124
    ],
    "C:\\Users\\LG\\GitHub\\loader-manual\\.docusaurus\\docusaurus-plugin-content-docs\\loader-manual-docs-spa-vue-a72.json": [
      125
    ],
    "C:\\Users\\LG\\GitHub\\loader-manual\\.docusaurus\\docusaurus-plugin-content-pages\\loader-manual-home-features-bcc.json": [
      126
    ],
    "C:\\Users\\LG\\GitHub\\loader-manual\\.docusaurus\\docusaurus-plugin-content-pages\\loader-manual-home-header-c75.json": [
      127
    ],
    "C:\\Users\\LG\\GitHub\\loader-manual\\.docusaurus\\docusaurus-plugin-content-blog\\loader-manual-blog-release-0-0-9-43c.json": [
      128
    ],
    "C:\\Users\\LG\\GitHub\\loader-manual\\.docusaurus\\docusaurus-plugin-content-blog\\loader-manual-blog-release-1-1-14-5a8.json": [
      129
    ],
    "C:\\Users\\LG\\GitHub\\loader-manual\\.docusaurus\\docusaurus-plugin-content-blog\\loader-manual-blog-release-1-1-15-8ba.json": [
      130
    ],
    "C:\\Users\\LG\\GitHub\\loader-manual\\.docusaurus\\docusaurus-plugin-content-blog\\loader-manual-blog-release-1-1-16-1b3.json": [
      131
    ],
    "C:\\Users\\LG\\GitHub\\loader-manual\\.docusaurus\\docusaurus-plugin-content-blog\\loader-manual-blog-release-1-1-18-aab.json": [
      132
    ],
    "C:\\Users\\LG\\GitHub\\loader-manual\\.docusaurus\\docusaurus-plugin-content-blog\\loader-manual-blog-release-1-1-19-acd.json": [
      133
    ],
    "C:\\Users\\LG\\GitHub\\loader-manual\\.docusaurus\\docusaurus-plugin-content-blog\\loader-manual-blog-release-1-1-21-f1b.json": [
      134
    ],
    "C:\\Users\\LG\\GitHub\\loader-manual\\.docusaurus\\docusaurus-plugin-content-blog\\loader-manual-blog-release-1-1-22-dda.json": [
      135
    ],
    "C:\\Users\\LG\\GitHub\\loader-manual\\.docusaurus\\docusaurus-plugin-content-blog\\loader-manual-blog-release-1-1-23-77d.json": [
      136
    ],
    "C:\\Users\\LG\\GitHub\\loader-manual\\.docusaurus\\docusaurus-plugin-content-blog\\loader-manual-blog-release-1-1-24-8bf.json": [
      137
    ],
    "C:\\Users\\LG\\GitHub\\loader-manual\\.docusaurus\\docusaurus-plugin-content-blog\\loader-manual-blog-release-1-1-25-99e.json": [
      138
    ],
    "C:\\Users\\LG\\GitHub\\loader-manual\\.docusaurus\\docusaurus-plugin-content-blog\\loader-manual-blog-release-1-2-0-105.json": [
      139
    ],
    "C:\\Users\\LG\\GitHub\\loader-manual\\.docusaurus\\docusaurus-plugin-content-blog\\loader-manual-blog-release-1-3-0-3d3.json": [
      140
    ],
    "C:\\Users\\LG\\GitHub\\loader-manual\\.docusaurus\\docusaurus-plugin-content-blog\\loader-manual-blog-release-1-3-1-e7a.json": [
      141
    ],
    "C:\\Users\\LG\\GitHub\\loader-manual\\.docusaurus\\docusaurus-plugin-content-blog\\loader-manual-blog-release-1-3-2-fe8.json": [
      142
    ],
    "runtime~main": [
      74,
      143
    ],
    "C:\\Users\\LG\\GitHub\\loader-manual\\.docusaurus\\docusaurus-plugin-content-blog\\loader-manual-blog-tags-tags-446.json": [
      144
    ],
    "docsearch.js": [
      145
    ],
    "@theme/NotFound": [
      0,
      1,
      146
    ]
  },
  "assets": {
    "0": {
      "js": [
        {
          "file": "0.8755f07b1eb37609ef58.js",
          "hash": "8755f07b1eb37609ef58",
          "publicPath": "/loader-manual/0.8755f07b1eb37609ef58.js"
        }
      ]
    },
    "1": {
      "css": [
        {
          "file": "1.9944869deaf6bb50a828.css",
          "hash": "9944869deaf6bb50a828",
          "publicPath": "/loader-manual/1.9944869deaf6bb50a828.css"
        }
      ],
      "js": [
        {
          "file": "1.9944869deaf6bb50a828.js",
          "hash": "9944869deaf6bb50a828",
          "publicPath": "/loader-manual/1.9944869deaf6bb50a828.js"
        }
      ]
    },
    "2": {
      "css": [
        {
          "file": "2.8dc0e0c71a862f2c2fec.css",
          "hash": "8dc0e0c71a862f2c2fec",
          "publicPath": "/loader-manual/2.8dc0e0c71a862f2c2fec.css"
        }
      ],
      "js": [
        {
          "file": "2.8dc0e0c71a862f2c2fec.js",
          "hash": "8dc0e0c71a862f2c2fec",
          "publicPath": "/loader-manual/2.8dc0e0c71a862f2c2fec.js"
        }
      ]
    },
    "3": {
      "js": [
        {
          "file": "3.9210f53ab5d22c68b1fb.js",
          "hash": "9210f53ab5d22c68b1fb",
          "publicPath": "/loader-manual/3.9210f53ab5d22c68b1fb.js"
        }
      ]
    },
    "6": {
      "css": [
        {
          "file": "component---c-users-lg-git-hub-loader-manual-src-pages-index-jsb-47-848.ee8f03b9539ab9123a4c.css",
          "hash": "ee8f03b9539ab9123a4c",
          "publicPath": "/loader-manual/component---c-users-lg-git-hub-loader-manual-src-pages-index-jsb-47-848.ee8f03b9539ab9123a4c.css"
        }
      ],
      "js": [
        {
          "file": "component---c-users-lg-git-hub-loader-manual-src-pages-index-jsb-47-848.ee8f03b9539ab9123a4c.js",
          "hash": "ee8f03b9539ab9123a4c",
          "publicPath": "/loader-manual/component---c-users-lg-git-hub-loader-manual-src-pages-index-jsb-47-848.ee8f03b9539ab9123a4c.js"
        }
      ]
    },
    "7": {
      "js": [
        {
          "file": "component---theme-blog-list-pagea-6-a-7ba.26ed23866f731a1b4f42.js",
          "hash": "26ed23866f731a1b4f42",
          "publicPath": "/loader-manual/component---theme-blog-list-pagea-6-a-7ba.26ed23866f731a1b4f42.js"
        }
      ]
    },
    "8": {
      "js": [
        {
          "file": "component---theme-blog-post-pageccc-cab.7ddcb0441adae3315a5c.js",
          "hash": "7ddcb0441adae3315a5c",
          "publicPath": "/loader-manual/component---theme-blog-post-pageccc-cab.7ddcb0441adae3315a5c.js"
        }
      ]
    },
    "9": {
      "js": [
        {
          "file": "component---theme-blog-tags-list-page-01-a-d0b.ac932a1a882056e307e1.js",
          "hash": "ac932a1a882056e307e1",
          "publicPath": "/loader-manual/component---theme-blog-tags-list-page-01-a-d0b.ac932a1a882056e307e1.js"
        }
      ]
    },
    "10": {
      "js": [
        {
          "file": "component---theme-blog-tags-posts-page-687-b6c.083389f4d2df02592958.js",
          "hash": "083389f4d2df02592958",
          "publicPath": "/loader-manual/component---theme-blog-tags-posts-page-687-b6c.083389f4d2df02592958.js"
        }
      ]
    },
    "11": {
      "css": [
        {
          "file": "component---theme-doc-legacy-item-031-769.dc157ca1ead76a4603d8.css",
          "hash": "dc157ca1ead76a4603d8",
          "publicPath": "/loader-manual/component---theme-doc-legacy-item-031-769.dc157ca1ead76a4603d8.css"
        }
      ],
      "js": [
        {
          "file": "component---theme-doc-legacy-item-031-769.dc157ca1ead76a4603d8.js",
          "hash": "dc157ca1ead76a4603d8",
          "publicPath": "/loader-manual/component---theme-doc-legacy-item-031-769.dc157ca1ead76a4603d8.js"
        }
      ]
    },
    "12": {
      "css": [
        {
          "file": "component---theme-doc-legacy-page-9-e-7-ca5.bff7b2376145193315b9.css",
          "hash": "bff7b2376145193315b9",
          "publicPath": "/loader-manual/component---theme-doc-legacy-page-9-e-7-ca5.bff7b2376145193315b9.css"
        }
      ],
      "js": [
        {
          "file": "component---theme-doc-legacy-page-9-e-7-ca5.bff7b2376145193315b9.js",
          "hash": "bff7b2376145193315b9",
          "publicPath": "/loader-manual/component---theme-doc-legacy-page-9-e-7-ca5.bff7b2376145193315b9.js"
        }
      ]
    },
    "13": {
      "js": [
        {
          "file": "content---loader-manual-blog-142-205.077869d10895dde8e75f.js",
          "hash": "077869d10895dde8e75f",
          "publicPath": "/loader-manual/content---loader-manual-blog-142-205.077869d10895dde8e75f.js"
        }
      ]
    },
    "14": {
      "js": [
        {
          "file": "content---loader-manual-blog-2-ae-f96.f8452bf5a1604c5d03e0.js",
          "hash": "f8452bf5a1604c5d03e0",
          "publicPath": "/loader-manual/content---loader-manual-blog-2-ae-f96.f8452bf5a1604c5d03e0.js"
        }
      ]
    },
    "15": {
      "js": [
        {
          "file": "content---loader-manual-blog-2-f-7-294.e81624aa003d4b8b56f2.js",
          "hash": "e81624aa003d4b8b56f2",
          "publicPath": "/loader-manual/content---loader-manual-blog-2-f-7-294.e81624aa003d4b8b56f2.js"
        }
      ]
    },
    "16": {
      "js": [
        {
          "file": "content---loader-manual-blog-3-c-8-54e.2e5d60875733b781ed10.js",
          "hash": "2e5d60875733b781ed10",
          "publicPath": "/loader-manual/content---loader-manual-blog-3-c-8-54e.2e5d60875733b781ed10.js"
        }
      ]
    },
    "17": {
      "js": [
        {
          "file": "content---loader-manual-blog-365-9f4.c63f3d9b89262e9b0793.js",
          "hash": "c63f3d9b89262e9b0793",
          "publicPath": "/loader-manual/content---loader-manual-blog-365-9f4.c63f3d9b89262e9b0793.js"
        }
      ]
    },
    "18": {
      "js": [
        {
          "file": "content---loader-manual-blog-386-4b7.73fad2a0945987cefee4.js",
          "hash": "73fad2a0945987cefee4",
          "publicPath": "/loader-manual/content---loader-manual-blog-386-4b7.73fad2a0945987cefee4.js"
        }
      ]
    },
    "19": {
      "js": [
        {
          "file": "content---loader-manual-blog-5-b-7-59c.79014cc23a1d8c27ac30.js",
          "hash": "79014cc23a1d8c27ac30",
          "publicPath": "/loader-manual/content---loader-manual-blog-5-b-7-59c.79014cc23a1d8c27ac30.js"
        }
      ]
    },
    "20": {
      "js": [
        {
          "file": "content---loader-manual-blog-6-f-4-63c.a0a239024cd833037a85.js",
          "hash": "a0a239024cd833037a85",
          "publicPath": "/loader-manual/content---loader-manual-blog-6-f-4-63c.a0a239024cd833037a85.js"
        }
      ]
    },
    "21": {
      "js": [
        {
          "file": "content---loader-manual-blog-871-91d.acf20a0ecb739480d1d7.js",
          "hash": "acf20a0ecb739480d1d7",
          "publicPath": "/loader-manual/content---loader-manual-blog-871-91d.acf20a0ecb739480d1d7.js"
        }
      ]
    },
    "22": {
      "js": [
        {
          "file": "content---loader-manual-blog-997-81c.81c717a501923fa781b3.js",
          "hash": "81c717a501923fa781b3",
          "publicPath": "/loader-manual/content---loader-manual-blog-997-81c.81c717a501923fa781b3.js"
        }
      ]
    },
    "23": {
      "js": [
        {
          "file": "content---loader-manual-blog-page-2-a-27-e84.e6d442c6235c5e84295b.js",
          "hash": "e6d442c6235c5e84295b",
          "publicPath": "/loader-manual/content---loader-manual-blog-page-2-a-27-e84.e6d442c6235c5e84295b.js"
        }
      ]
    },
    "24": {
      "js": [
        {
          "file": "content---loader-manual-blog-page-2-dd-9-33c.c5a321837078a410340b.js",
          "hash": "c5a321837078a410340b",
          "publicPath": "/loader-manual/content---loader-manual-blog-page-2-dd-9-33c.c5a321837078a410340b.js"
        }
      ]
    },
    "25": {
      "js": [
        {
          "file": "content---loader-manual-blog-page-2-e-5-a-546.7431a97350d29669eb91.js",
          "hash": "7431a97350d29669eb91",
          "publicPath": "/loader-manual/content---loader-manual-blog-page-2-e-5-a-546.7431a97350d29669eb91.js"
        }
      ]
    },
    "26": {
      "js": [
        {
          "file": "content---loader-manual-blog-page-20-ef-79b.d9c1741918ff78e2ae25.js",
          "hash": "d9c1741918ff78e2ae25",
          "publicPath": "/loader-manual/content---loader-manual-blog-page-20-ef-79b.d9c1741918ff78e2ae25.js"
        }
      ]
    },
    "27": {
      "js": [
        {
          "file": "content---loader-manual-blog-page-228-c-2d5.65ddc1ec3fc9c0a979d3.js",
          "hash": "65ddc1ec3fc9c0a979d3",
          "publicPath": "/loader-manual/content---loader-manual-blog-page-228-c-2d5.65ddc1ec3fc9c0a979d3.js"
        }
      ]
    },
    "28": {
      "js": [
        {
          "file": "content---loader-manual-blog-page-24-c-3-5e3.00c7bae3f2698999a4b7.js",
          "hash": "00c7bae3f2698999a4b7",
          "publicPath": "/loader-manual/content---loader-manual-blog-page-24-c-3-5e3.00c7bae3f2698999a4b7.js"
        }
      ]
    },
    "29": {
      "js": [
        {
          "file": "content---loader-manual-blog-release-0-0-9-ae-7-047.2c651f9318b184770511.js",
          "hash": "2c651f9318b184770511",
          "publicPath": "/loader-manual/content---loader-manual-blog-release-0-0-9-ae-7-047.2c651f9318b184770511.js"
        }
      ]
    },
    "30": {
      "js": [
        {
          "file": "content---loader-manual-blog-release-1-1-14858-e1f.0247b25a135a021b08aa.js",
          "hash": "0247b25a135a021b08aa",
          "publicPath": "/loader-manual/content---loader-manual-blog-release-1-1-14858-e1f.0247b25a135a021b08aa.js"
        }
      ]
    },
    "31": {
      "js": [
        {
          "file": "content---loader-manual-blog-release-1-1-15495-cfc.9ee1fd1cbb2f4f69e675.js",
          "hash": "9ee1fd1cbb2f4f69e675",
          "publicPath": "/loader-manual/content---loader-manual-blog-release-1-1-15495-cfc.9ee1fd1cbb2f4f69e675.js"
        }
      ]
    },
    "32": {
      "js": [
        {
          "file": "content---loader-manual-blog-release-1-1-16-f-80-13d.89d8a40f7f267465330e.js",
          "hash": "89d8a40f7f267465330e",
          "publicPath": "/loader-manual/content---loader-manual-blog-release-1-1-16-f-80-13d.89d8a40f7f267465330e.js"
        }
      ]
    },
    "33": {
      "js": [
        {
          "file": "content---loader-manual-blog-release-1-1-18-f-76-9ad.4cd50e4912168a561e33.js",
          "hash": "4cd50e4912168a561e33",
          "publicPath": "/loader-manual/content---loader-manual-blog-release-1-1-18-f-76-9ad.4cd50e4912168a561e33.js"
        }
      ]
    },
    "34": {
      "js": [
        {
          "file": "content---loader-manual-blog-release-1-1-1951-f-73e.a756e13661360728bbf4.js",
          "hash": "a756e13661360728bbf4",
          "publicPath": "/loader-manual/content---loader-manual-blog-release-1-1-1951-f-73e.a756e13661360728bbf4.js"
        }
      ]
    },
    "35": {
      "js": [
        {
          "file": "content---loader-manual-blog-release-1-1-21598-a23.f581a58bd5cf193084b6.js",
          "hash": "f581a58bd5cf193084b6",
          "publicPath": "/loader-manual/content---loader-manual-blog-release-1-1-21598-a23.f581a58bd5cf193084b6.js"
        }
      ]
    },
    "36": {
      "js": [
        {
          "file": "content---loader-manual-blog-release-1-1-22-e-86-50e.8098adf2c0d54f9eea4f.js",
          "hash": "8098adf2c0d54f9eea4f",
          "publicPath": "/loader-manual/content---loader-manual-blog-release-1-1-22-e-86-50e.8098adf2c0d54f9eea4f.js"
        }
      ]
    },
    "37": {
      "js": [
        {
          "file": "content---loader-manual-blog-release-1-1-23-deb-5fc.4629a6e80b001fc13ab1.js",
          "hash": "4629a6e80b001fc13ab1",
          "publicPath": "/loader-manual/content---loader-manual-blog-release-1-1-23-deb-5fc.4629a6e80b001fc13ab1.js"
        }
      ]
    },
    "38": {
      "js": [
        {
          "file": "content---loader-manual-blog-release-1-1-248-db-10f.f7d9d33783b77ce938bf.js",
          "hash": "f7d9d33783b77ce938bf",
          "publicPath": "/loader-manual/content---loader-manual-blog-release-1-1-248-db-10f.f7d9d33783b77ce938bf.js"
        }
      ]
    },
    "39": {
      "js": [
        {
          "file": "content---loader-manual-blog-release-1-1-25597-e28.20d7b83da198b8003a08.js",
          "hash": "20d7b83da198b8003a08",
          "publicPath": "/loader-manual/content---loader-manual-blog-release-1-1-25597-e28.20d7b83da198b8003a08.js"
        }
      ]
    },
    "40": {
      "js": [
        {
          "file": "content---loader-manual-blog-release-1-2-0-ead-20e.5d2138bf883b0ddd5dd0.js",
          "hash": "5d2138bf883b0ddd5dd0",
          "publicPath": "/loader-manual/content---loader-manual-blog-release-1-2-0-ead-20e.5d2138bf883b0ddd5dd0.js"
        }
      ]
    },
    "41": {
      "js": [
        {
          "file": "content---loader-manual-blog-release-1-3-0-f-08-d35.d9336c1fb06e134a7bcd.js",
          "hash": "d9336c1fb06e134a7bcd",
          "publicPath": "/loader-manual/content---loader-manual-blog-release-1-3-0-f-08-d35.d9336c1fb06e134a7bcd.js"
        }
      ]
    },
    "42": {
      "js": [
        {
          "file": "content---loader-manual-blog-release-1-3-1858-a1c.8ff7244de951919a9d06.js",
          "hash": "8ff7244de951919a9d06",
          "publicPath": "/loader-manual/content---loader-manual-blog-release-1-3-1858-a1c.8ff7244de951919a9d06.js"
        }
      ]
    },
    "43": {
      "js": [
        {
          "file": "content---loader-manual-blog-release-1-3-2-d-4-a-ddd.65ead9fa38228f3b4ac6.js",
          "hash": "65ead9fa38228f3b4ac6",
          "publicPath": "/loader-manual/content---loader-manual-blog-release-1-3-2-d-4-a-ddd.65ead9fa38228f3b4ac6.js"
        }
      ]
    },
    "44": {
      "js": [
        {
          "file": "content---loader-manual-blog-release-1-3-3542-3a1.df3461d00fa6fc3ee788.js",
          "hash": "df3461d00fa6fc3ee788",
          "publicPath": "/loader-manual/content---loader-manual-blog-release-1-3-3542-3a1.df3461d00fa6fc3ee788.js"
        }
      ]
    },
    "45": {
      "js": [
        {
          "file": "content---loader-manual-docs-adv-configc-29-c1d.b66b93e9bad2c5c94d27.js",
          "hash": "b66b93e9bad2c5c94d27",
          "publicPath": "/loader-manual/content---loader-manual-docs-adv-configc-29-c1d.b66b93e9bad2c5c94d27.js"
        }
      ]
    },
    "46": {
      "js": [
        {
          "file": "content---loader-manual-docs-adv-events-05-a-255.ed0651f78b84aec518e3.js",
          "hash": "ed0651f78b84aec518e3",
          "publicPath": "/loader-manual/content---loader-manual-docs-adv-events-05-a-255.ed0651f78b84aec518e3.js"
        }
      ]
    },
    "47": {
      "js": [
        {
          "file": "content---loader-manual-docs-adv-load-0-b-4-b82.cedd54fc5c25326c119c.js",
          "hash": "cedd54fc5c25326c119c",
          "publicPath": "/loader-manual/content---loader-manual-docs-adv-load-0-b-4-b82.cedd54fc5c25326c119c.js"
        }
      ]
    },
    "48": {
      "js": [
        {
          "file": "content---loader-manual-docs-adv-registry-185-0b9.1a4932e0650e9ce3c215.js",
          "hash": "1a4932e0650e9ce3c215",
          "publicPath": "/loader-manual/content---loader-manual-docs-adv-registry-185-0b9.1a4932e0650e9ce3c215.js"
        }
      ]
    },
    "49": {
      "js": [
        {
          "file": "content---loader-manual-docs-adv-unload-2-e-9-f64.66083cad865512463570.js",
          "hash": "66083cad865512463570",
          "publicPath": "/loader-manual/content---loader-manual-docs-adv-unload-2-e-9-f64.66083cad865512463570.js"
        }
      ]
    },
    "50": {
      "js": [
        {
          "file": "content---loader-manual-docs-basic-getting-started-34-f-f71.720d1b97c03089730ffd.js",
          "hash": "720d1b97c03089730ffd",
          "publicPath": "/loader-manual/content---loader-manual-docs-basic-getting-started-34-f-f71.720d1b97c03089730ffd.js"
        }
      ]
    },
    "51": {
      "js": [
        {
          "file": "content---loader-manual-docs-demo-angular-demoe-84-e89.999a0480eeba1915aa3c.js",
          "hash": "999a0480eeba1915aa3c",
          "publicPath": "/loader-manual/content---loader-manual-docs-demo-angular-demoe-84-e89.999a0480eeba1915aa3c.js"
        }
      ]
    },
    "52": {
      "js": [
        {
          "file": "content---loader-manual-docs-demo-ib-chart-angular-demo-158-0f2.cd252eb9be276b348d11.js",
          "hash": "cd252eb9be276b348d11",
          "publicPath": "/loader-manual/content---loader-manual-docs-demo-ib-chart-angular-demo-158-0f2.cd252eb9be276b348d11.js"
        }
      ]
    },
    "53": {
      "js": [
        {
          "file": "content---loader-manual-docs-demo-ib-chart-react-democ-63-fb3.590665a843a1aa5c4893.js",
          "hash": "590665a843a1aa5c4893",
          "publicPath": "/loader-manual/content---loader-manual-docs-demo-ib-chart-react-democ-63-fb3.590665a843a1aa5c4893.js"
        }
      ]
    },
    "54": {
      "js": [
        {
          "file": "content---loader-manual-docs-demo-ib-chart-vue-demo-7-d-6-b54.c8f0d08b6cc9ceb192e5.js",
          "hash": "c8f0d08b6cc9ceb192e5",
          "publicPath": "/loader-manual/content---loader-manual-docs-demo-ib-chart-vue-demo-7-d-6-b54.c8f0d08b6cc9ceb192e5.js"
        }
      ]
    },
    "55": {
      "js": [
        {
          "file": "content---loader-manual-docs-demo-ib-map-angular-demo-159-420.863d6c6ef3ebd748c5d3.js",
          "hash": "863d6c6ef3ebd748c5d3",
          "publicPath": "/loader-manual/content---loader-manual-docs-demo-ib-map-angular-demo-159-420.863d6c6ef3ebd748c5d3.js"
        }
      ]
    },
    "56": {
      "js": [
        {
          "file": "content---loader-manual-docs-demo-ib-map-react-demo-62-b-571.21740c1e4d90fbac8ce5.js",
          "hash": "21740c1e4d90fbac8ce5",
          "publicPath": "/loader-manual/content---loader-manual-docs-demo-ib-map-react-demo-62-b-571.21740c1e4d90fbac8ce5.js"
        }
      ]
    },
    "57": {
      "js": [
        {
          "file": "content---loader-manual-docs-demo-ib-map-vue-demo-372-7bd.de2f07966aa1dcd57275.js",
          "hash": "de2f07966aa1dcd57275",
          "publicPath": "/loader-manual/content---loader-manual-docs-demo-ib-map-vue-demo-372-7bd.de2f07966aa1dcd57275.js"
        }
      ]
    },
    "58": {
      "js": [
        {
          "file": "content---loader-manual-docs-demo-react-demo-338-a8f.48af62f49675007f3bfa.js",
          "hash": "48af62f49675007f3bfa",
          "publicPath": "/loader-manual/content---loader-manual-docs-demo-react-demo-338-a8f.48af62f49675007f3bfa.js"
        }
      ]
    },
    "59": {
      "js": [
        {
          "file": "content---loader-manual-docs-demo-vue-demo-772-77f.086550896a92f5a77503.js",
          "hash": "086550896a92f5a77503",
          "publicPath": "/loader-manual/content---loader-manual-docs-demo-vue-demo-772-77f.086550896a92f5a77503.js"
        }
      ]
    },
    "60": {
      "js": [
        {
          "file": "content---loader-manual-docs-etc-external-libb-96-d3f.81ace53946df9f80909e.js",
          "hash": "81ace53946df9f80909e",
          "publicPath": "/loader-manual/content---loader-manual-docs-etc-external-libb-96-d3f.81ace53946df9f80909e.js"
        }
      ]
    },
    "61": {
      "js": [
        {
          "file": "content---loader-manual-docs-etc-load-flow-239-176.e13decb4c1da370e5f82.js",
          "hash": "e13decb4c1da370e5f82",
          "publicPath": "/loader-manual/content---loader-manual-docs-etc-load-flow-239-176.e13decb4c1da370e5f82.js"
        }
      ]
    },
    "62": {
      "js": [
        {
          "file": "content---loader-manual-docs-etc-starter-packages-327-0d4.32d0286c97cc86ae7414.js",
          "hash": "32d0286c97cc86ae7414",
          "publicPath": "/loader-manual/content---loader-manual-docs-etc-starter-packages-327-0d4.32d0286c97cc86ae7414.js"
        }
      ]
    },
    "63": {
      "js": [
        {
          "file": "content---loader-manual-docs-etc-trouble-shooting-62-f-48e.1b8c69490e7a0f3794d2.js",
          "hash": "1b8c69490e7a0f3794d2",
          "publicPath": "/loader-manual/content---loader-manual-docs-etc-trouble-shooting-62-f-48e.1b8c69490e7a0f3794d2.js"
        }
      ]
    },
    "64": {
      "js": [
        {
          "file": "content---loader-manual-docs-ibchart-create-chartd-77-728.7e44aa7d64278b5ebda0.js",
          "hash": "7e44aa7d64278b5ebda0",
          "publicPath": "/loader-manual/content---loader-manual-docs-ibchart-create-chartd-77-728.7e44aa7d64278b5ebda0.js"
        }
      ]
    },
    "65": {
      "js": [
        {
          "file": "content---loader-manual-docs-ibchart-remove-chartdca-af7.753d7f007c0e23103f44.js",
          "hash": "753d7f007c0e23103f44",
          "publicPath": "/loader-manual/content---loader-manual-docs-ibchart-remove-chartdca-af7.753d7f007c0e23103f44.js"
        }
      ]
    },
    "66": {
      "js": [
        {
          "file": "content---loader-manual-docs-ibmap-create-mapf-81-4d4.2f011be1de6bf0dc5304.js",
          "hash": "2f011be1de6bf0dc5304",
          "publicPath": "/loader-manual/content---loader-manual-docs-ibmap-create-mapf-81-4d4.2f011be1de6bf0dc5304.js"
        }
      ]
    },
    "67": {
      "js": [
        {
          "file": "content---loader-manual-docs-ibmap-remove-map-1-b-7-3de.7b112f23444281282d16.js",
          "hash": "7b112f23444281282d16",
          "publicPath": "/loader-manual/content---loader-manual-docs-ibmap-remove-map-1-b-7-3de.7b112f23444281282d16.js"
        }
      ]
    },
    "68": {
      "js": [
        {
          "file": "content---loader-manual-docs-ibsheet-create-sheet-714-291.7b0f5aaadc522a4c9ced.js",
          "hash": "7b0f5aaadc522a4c9ced",
          "publicPath": "/loader-manual/content---loader-manual-docs-ibsheet-create-sheet-714-291.7b0f5aaadc522a4c9ced.js"
        }
      ]
    },
    "69": {
      "js": [
        {
          "file": "content---loader-manual-docs-ibsheet-remove-sheet-72-d-73f.e8c322fde474a736518b.js",
          "hash": "e8c322fde474a736518b",
          "publicPath": "/loader-manual/content---loader-manual-docs-ibsheet-remove-sheet-72-d-73f.e8c322fde474a736518b.js"
        }
      ]
    },
    "70": {
      "js": [
        {
          "file": "content---loader-manual-docs-spa-angulara-61-8a0.31ca5e70f533a63135e2.js",
          "hash": "31ca5e70f533a63135e2",
          "publicPath": "/loader-manual/content---loader-manual-docs-spa-angulara-61-8a0.31ca5e70f533a63135e2.js"
        }
      ]
    },
    "71": {
      "js": [
        {
          "file": "content---loader-manual-docs-spa-react-6-ab-e62.13097db770ea48c53439.js",
          "hash": "13097db770ea48c53439",
          "publicPath": "/loader-manual/content---loader-manual-docs-spa-react-6-ab-e62.13097db770ea48c53439.js"
        }
      ]
    },
    "72": {
      "js": [
        {
          "file": "content---loader-manual-docs-spa-vue-740-14a.b3dd2de7c242ddf2dad6.js",
          "hash": "b3dd2de7c242ddf2dad6",
          "publicPath": "/loader-manual/content---loader-manual-docs-spa-vue-740-14a.b3dd2de7c242ddf2dad6.js"
        }
      ]
    },
    "73": {
      "js": [
        {
          "file": "docsMetadata---loader-manual-docsc-5-e-dcf.a79773d35b46b7add37c.js",
          "hash": "a79773d35b46b7add37c",
          "publicPath": "/loader-manual/docsMetadata---loader-manual-docsc-5-e-dcf.a79773d35b46b7add37c.js"
        }
      ]
    },
    "74": {
      "css": [
        {
          "file": "main.2ff88967c8383d9c3d16.css",
          "hash": "2ff88967c8383d9c3d16",
          "publicPath": "/loader-manual/main.2ff88967c8383d9c3d16.css"
        }
      ],
      "js": [
        {
          "file": "main.2ff88967c8383d9c3d16.js",
          "hash": "2ff88967c8383d9c3d16",
          "publicPath": "/loader-manual/main.2ff88967c8383d9c3d16.js"
        }
      ]
    },
    "75": {
      "js": [
        {
          "file": "metadata---loader-manual-10-a-999.e552afd3e7a914b0c8ce.js",
          "hash": "e552afd3e7a914b0c8ce",
          "publicPath": "/loader-manual/metadata---loader-manual-10-a-999.e552afd3e7a914b0c8ce.js"
        }
      ]
    },
    "76": {
      "js": [
        {
          "file": "metadata---loader-manual-blog-9-c-4-b79.e9ac2a84032c8bc92585.js",
          "hash": "e9ac2a84032c8bc92585",
          "publicPath": "/loader-manual/metadata---loader-manual-blog-9-c-4-b79.e9ac2a84032c8bc92585.js"
        }
      ]
    },
    "77": {
      "js": [
        {
          "file": "metadata---loader-manual-blog-page-2-c-0-f-b3e.c7e613a6acc1619e0709.js",
          "hash": "c7e613a6acc1619e0709",
          "publicPath": "/loader-manual/metadata---loader-manual-blog-page-2-c-0-f-b3e.c7e613a6acc1619e0709.js"
        }
      ]
    },
    "78": {
      "js": [
        {
          "file": "metadata---loader-manual-blog-release-1-3-36-fb-ae1.c41c2c740ba8e1fb3a3d.js",
          "hash": "c41c2c740ba8e1fb3a3d",
          "publicPath": "/loader-manual/metadata---loader-manual-blog-release-1-3-36-fb-ae1.c41c2c740ba8e1fb3a3d.js"
        }
      ]
    },
    "79": {
      "js": [
        {
          "file": "metadata---loader-manual-blog-tags-ibsheet-loader-727-18c.3e13058f143f9af65643.js",
          "hash": "3e13058f143f9af65643",
          "publicPath": "/loader-manual/metadata---loader-manual-blog-tags-ibsheet-loader-727-18c.3e13058f143f9af65643.js"
        }
      ]
    },
    "80": {
      "js": [
        {
          "file": "metadata---loader-manual-blog-tags-npmbfb-5ca.33a17125b1524eabea93.js",
          "hash": "33a17125b1524eabea93",
          "publicPath": "/loader-manual/metadata---loader-manual-blog-tags-npmbfb-5ca.33a17125b1524eabea93.js"
        }
      ]
    },
    "81": {
      "js": [
        {
          "file": "metadata---loader-manual-blog-tags-release-277-19e.488d2bb25c6ebd211cdc.js",
          "hash": "488d2bb25c6ebd211cdc",
          "publicPath": "/loader-manual/metadata---loader-manual-blog-tags-release-277-19e.488d2bb25c6ebd211cdc.js"
        }
      ]
    },
    "82": {
      "js": [
        {
          "file": "metadata---loader-manual-blog-tags-v-0-0-9-f-45-f0c.739a6dfe2dc898a2f36b.js",
          "hash": "739a6dfe2dc898a2f36b",
          "publicPath": "/loader-manual/metadata---loader-manual-blog-tags-v-0-0-9-f-45-f0c.739a6dfe2dc898a2f36b.js"
        }
      ]
    },
    "83": {
      "js": [
        {
          "file": "metadata---loader-manual-blog-tags-v-1-1-14-f-6-e-405.441f77919caa5c2cb9ee.js",
          "hash": "441f77919caa5c2cb9ee",
          "publicPath": "/loader-manual/metadata---loader-manual-blog-tags-v-1-1-14-f-6-e-405.441f77919caa5c2cb9ee.js"
        }
      ]
    },
    "84": {
      "js": [
        {
          "file": "metadata---loader-manual-blog-tags-v-1-1-156-d-2-db5.d8396b12d1ef1cd446e1.js",
          "hash": "d8396b12d1ef1cd446e1",
          "publicPath": "/loader-manual/metadata---loader-manual-blog-tags-v-1-1-156-d-2-db5.d8396b12d1ef1cd446e1.js"
        }
      ]
    },
    "85": {
      "js": [
        {
          "file": "metadata---loader-manual-blog-tags-v-1-1-16-b-1-d-371.91d35b815e626a1b1db6.js",
          "hash": "91d35b815e626a1b1db6",
          "publicPath": "/loader-manual/metadata---loader-manual-blog-tags-v-1-1-16-b-1-d-371.91d35b815e626a1b1db6.js"
        }
      ]
    },
    "86": {
      "js": [
        {
          "file": "metadata---loader-manual-blog-tags-v-1-1-18-f-86-d67.e425afecb91493f0ce03.js",
          "hash": "e425afecb91493f0ce03",
          "publicPath": "/loader-manual/metadata---loader-manual-blog-tags-v-1-1-18-f-86-d67.e425afecb91493f0ce03.js"
        }
      ]
    },
    "87": {
      "js": [
        {
          "file": "metadata---loader-manual-blog-tags-v-1-1-19265-f1a.e45737fd9396a574cf31.js",
          "hash": "e45737fd9396a574cf31",
          "publicPath": "/loader-manual/metadata---loader-manual-blog-tags-v-1-1-19265-f1a.e45737fd9396a574cf31.js"
        }
      ]
    },
    "88": {
      "js": [
        {
          "file": "metadata---loader-manual-blog-tags-v-1-1-21-c-8-d-395.bbb96426d57b4cccf09e.js",
          "hash": "bbb96426d57b4cccf09e",
          "publicPath": "/loader-manual/metadata---loader-manual-blog-tags-v-1-1-21-c-8-d-395.bbb96426d57b4cccf09e.js"
        }
      ]
    },
    "89": {
      "js": [
        {
          "file": "metadata---loader-manual-blog-tags-v-1-1-22-ee-2-758.8d0465bb58bf265c6fb1.js",
          "hash": "8d0465bb58bf265c6fb1",
          "publicPath": "/loader-manual/metadata---loader-manual-blog-tags-v-1-1-22-ee-2-758.8d0465bb58bf265c6fb1.js"
        }
      ]
    },
    "90": {
      "js": [
        {
          "file": "metadata---loader-manual-blog-tags-v-1-1-23-cca-b27.a5199a6911461cb2b429.js",
          "hash": "a5199a6911461cb2b429",
          "publicPath": "/loader-manual/metadata---loader-manual-blog-tags-v-1-1-23-cca-b27.a5199a6911461cb2b429.js"
        }
      ]
    },
    "91": {
      "js": [
        {
          "file": "metadata---loader-manual-blog-tags-v-1-1-243-eb-544.2989913d7b75598a68ad.js",
          "hash": "2989913d7b75598a68ad",
          "publicPath": "/loader-manual/metadata---loader-manual-blog-tags-v-1-1-243-eb-544.2989913d7b75598a68ad.js"
        }
      ]
    },
    "92": {
      "js": [
        {
          "file": "metadata---loader-manual-blog-tags-v-1-1-25-d-62-169.8a21aa88c6193111f0f4.js",
          "hash": "8a21aa88c6193111f0f4",
          "publicPath": "/loader-manual/metadata---loader-manual-blog-tags-v-1-1-25-d-62-169.8a21aa88c6193111f0f4.js"
        }
      ]
    },
    "93": {
      "js": [
        {
          "file": "metadata---loader-manual-blog-tags-v-1-2-0-f-38-568.26d297bc9ef3603e613a.js",
          "hash": "26d297bc9ef3603e613a",
          "publicPath": "/loader-manual/metadata---loader-manual-blog-tags-v-1-2-0-f-38-568.26d297bc9ef3603e613a.js"
        }
      ]
    },
    "94": {
      "js": [
        {
          "file": "metadata---loader-manual-blog-tags-v-1-3-0418-b3f.1e538e83cafce090511b.js",
          "hash": "1e538e83cafce090511b",
          "publicPath": "/loader-manual/metadata---loader-manual-blog-tags-v-1-3-0418-b3f.1e538e83cafce090511b.js"
        }
      ]
    },
    "95": {
      "js": [
        {
          "file": "metadata---loader-manual-blog-tags-v-1-3-14-b-7-858.a9f5cbb112351143f513.js",
          "hash": "a9f5cbb112351143f513",
          "publicPath": "/loader-manual/metadata---loader-manual-blog-tags-v-1-3-14-b-7-858.a9f5cbb112351143f513.js"
        }
      ]
    },
    "96": {
      "js": [
        {
          "file": "metadata---loader-manual-blog-tags-v-1-3-2070-dfc.8d447a482a16dc8715f1.js",
          "hash": "8d447a482a16dc8715f1",
          "publicPath": "/loader-manual/metadata---loader-manual-blog-tags-v-1-3-2070-dfc.8d447a482a16dc8715f1.js"
        }
      ]
    },
    "97": {
      "js": [
        {
          "file": "metadata---loader-manual-blog-tags-v-1-3-3-ea-6-0f5.a2de16f8e16f2a73bd24.js",
          "hash": "a2de16f8e16f2a73bd24",
          "publicPath": "/loader-manual/metadata---loader-manual-blog-tags-v-1-3-3-ea-6-0f5.a2de16f8e16f2a73bd24.js"
        }
      ]
    },
    "98": {
      "js": [
        {
          "file": "metadata---loader-manual-docs-adv-configfdc-7a0.fa785b476dc3cd7ea8e8.js",
          "hash": "fa785b476dc3cd7ea8e8",
          "publicPath": "/loader-manual/metadata---loader-manual-docs-adv-configfdc-7a0.fa785b476dc3cd7ea8e8.js"
        }
      ]
    },
    "99": {
      "js": [
        {
          "file": "metadata---loader-manual-docs-adv-events-93-e-f63.8edd7803a5107fadd167.js",
          "hash": "8edd7803a5107fadd167",
          "publicPath": "/loader-manual/metadata---loader-manual-docs-adv-events-93-e-f63.8edd7803a5107fadd167.js"
        }
      ]
    },
    "100": {
      "js": [
        {
          "file": "metadata---loader-manual-docs-adv-load-3-c-2-30f.32f0d997bec0b865030a.js",
          "hash": "32f0d997bec0b865030a",
          "publicPath": "/loader-manual/metadata---loader-manual-docs-adv-load-3-c-2-30f.32f0d997bec0b865030a.js"
        }
      ]
    },
    "101": {
      "js": [
        {
          "file": "metadata---loader-manual-docs-adv-registry-905-0bd.50e4c3fdfb5f81243cb7.js",
          "hash": "50e4c3fdfb5f81243cb7",
          "publicPath": "/loader-manual/metadata---loader-manual-docs-adv-registry-905-0bd.50e4c3fdfb5f81243cb7.js"
        }
      ]
    },
    "102": {
      "js": [
        {
          "file": "metadata---loader-manual-docs-adv-unload-451-890.cb8d128a39dee75347ac.js",
          "hash": "cb8d128a39dee75347ac",
          "publicPath": "/loader-manual/metadata---loader-manual-docs-adv-unload-451-890.cb8d128a39dee75347ac.js"
        }
      ]
    },
    "103": {
      "js": [
        {
          "file": "metadata---loader-manual-docs-basic-getting-started-614-5e7.2cfd62dcfefcdd11412f.js",
          "hash": "2cfd62dcfefcdd11412f",
          "publicPath": "/loader-manual/metadata---loader-manual-docs-basic-getting-started-614-5e7.2cfd62dcfefcdd11412f.js"
        }
      ]
    },
    "104": {
      "js": [
        {
          "file": "metadata---loader-manual-docs-demo-angular-demo-69-e-2e8.84b01cd41b3fbdf5fb0f.js",
          "hash": "84b01cd41b3fbdf5fb0f",
          "publicPath": "/loader-manual/metadata---loader-manual-docs-demo-angular-demo-69-e-2e8.84b01cd41b3fbdf5fb0f.js"
        }
      ]
    },
    "105": {
      "js": [
        {
          "file": "metadata---loader-manual-docs-demo-ib-chart-angular-demoa-28-db5.da773382f12ea5ca9a8e.js",
          "hash": "da773382f12ea5ca9a8e",
          "publicPath": "/loader-manual/metadata---loader-manual-docs-demo-ib-chart-angular-demoa-28-db5.da773382f12ea5ca9a8e.js"
        }
      ]
    },
    "106": {
      "js": [
        {
          "file": "metadata---loader-manual-docs-demo-ib-chart-react-demo-066-1d4.d57f00c78c147f23301c.js",
          "hash": "d57f00c78c147f23301c",
          "publicPath": "/loader-manual/metadata---loader-manual-docs-demo-ib-chart-react-demo-066-1d4.d57f00c78c147f23301c.js"
        }
      ]
    },
    "107": {
      "js": [
        {
          "file": "metadata---loader-manual-docs-demo-ib-chart-vue-demo-546-8e4.f090271a96da7e4987e3.js",
          "hash": "f090271a96da7e4987e3",
          "publicPath": "/loader-manual/metadata---loader-manual-docs-demo-ib-chart-vue-demo-546-8e4.f090271a96da7e4987e3.js"
        }
      ]
    },
    "108": {
      "js": [
        {
          "file": "metadata---loader-manual-docs-demo-ib-map-angular-demo-454-1e0.c9dd0733ad939b86e5e6.js",
          "hash": "c9dd0733ad939b86e5e6",
          "publicPath": "/loader-manual/metadata---loader-manual-docs-demo-ib-map-angular-demo-454-1e0.c9dd0733ad939b86e5e6.js"
        }
      ]
    },
    "109": {
      "js": [
        {
          "file": "metadata---loader-manual-docs-demo-ib-map-react-demo-563-cfa.5f5ad669bfbb699005ab.js",
          "hash": "5f5ad669bfbb699005ab",
          "publicPath": "/loader-manual/metadata---loader-manual-docs-demo-ib-map-react-demo-563-cfa.5f5ad669bfbb699005ab.js"
        }
      ]
    },
    "110": {
      "js": [
        {
          "file": "metadata---loader-manual-docs-demo-ib-map-vue-demob-59-d85.5ad80d70fb9f150feebf.js",
          "hash": "5ad80d70fb9f150feebf",
          "publicPath": "/loader-manual/metadata---loader-manual-docs-demo-ib-map-vue-demob-59-d85.5ad80d70fb9f150feebf.js"
        }
      ]
    },
    "111": {
      "js": [
        {
          "file": "metadata---loader-manual-docs-demo-react-demo-6-ee-497.e6df0c53369bf95fbbf9.js",
          "hash": "e6df0c53369bf95fbbf9",
          "publicPath": "/loader-manual/metadata---loader-manual-docs-demo-react-demo-6-ee-497.e6df0c53369bf95fbbf9.js"
        }
      ]
    },
    "112": {
      "js": [
        {
          "file": "metadata---loader-manual-docs-demo-vue-demo-292-0df.5ec8b6396eb80f9bf0ff.js",
          "hash": "5ec8b6396eb80f9bf0ff",
          "publicPath": "/loader-manual/metadata---loader-manual-docs-demo-vue-demo-292-0df.5ec8b6396eb80f9bf0ff.js"
        }
      ]
    },
    "113": {
      "js": [
        {
          "file": "metadata---loader-manual-docs-etc-external-lib-507-a49.fe1aaaed2e76e09ad1e1.js",
          "hash": "fe1aaaed2e76e09ad1e1",
          "publicPath": "/loader-manual/metadata---loader-manual-docs-etc-external-lib-507-a49.fe1aaaed2e76e09ad1e1.js"
        }
      ]
    },
    "114": {
      "js": [
        {
          "file": "metadata---loader-manual-docs-etc-load-flow-8-c-6-a10.54a0664bd914536c8788.js",
          "hash": "54a0664bd914536c8788",
          "publicPath": "/loader-manual/metadata---loader-manual-docs-etc-load-flow-8-c-6-a10.54a0664bd914536c8788.js"
        }
      ]
    },
    "115": {
      "js": [
        {
          "file": "metadata---loader-manual-docs-etc-starter-packages-125-7c2.89ec031286eb6fde24c1.js",
          "hash": "89ec031286eb6fde24c1",
          "publicPath": "/loader-manual/metadata---loader-manual-docs-etc-starter-packages-125-7c2.89ec031286eb6fde24c1.js"
        }
      ]
    },
    "116": {
      "js": [
        {
          "file": "metadata---loader-manual-docs-etc-trouble-shootingdb-2-4a8.607fecdbacd26770395c.js",
          "hash": "607fecdbacd26770395c",
          "publicPath": "/loader-manual/metadata---loader-manual-docs-etc-trouble-shootingdb-2-4a8.607fecdbacd26770395c.js"
        }
      ]
    },
    "117": {
      "js": [
        {
          "file": "metadata---loader-manual-docs-ibchart-create-chartffb-0e5.9d3680d85a91fca59fa8.js",
          "hash": "9d3680d85a91fca59fa8",
          "publicPath": "/loader-manual/metadata---loader-manual-docs-ibchart-create-chartffb-0e5.9d3680d85a91fca59fa8.js"
        }
      ]
    },
    "118": {
      "js": [
        {
          "file": "metadata---loader-manual-docs-ibchart-remove-chart-824-b35.c8d2991674277ab28448.js",
          "hash": "c8d2991674277ab28448",
          "publicPath": "/loader-manual/metadata---loader-manual-docs-ibchart-remove-chart-824-b35.c8d2991674277ab28448.js"
        }
      ]
    },
    "119": {
      "js": [
        {
          "file": "metadata---loader-manual-docs-ibmap-create-map-863-66e.d9c5b22cdf7429254aca.js",
          "hash": "d9c5b22cdf7429254aca",
          "publicPath": "/loader-manual/metadata---loader-manual-docs-ibmap-create-map-863-66e.d9c5b22cdf7429254aca.js"
        }
      ]
    },
    "120": {
      "js": [
        {
          "file": "metadata---loader-manual-docs-ibmap-remove-mapc-42-8a1.3749cd2adcf3267b2d08.js",
          "hash": "3749cd2adcf3267b2d08",
          "publicPath": "/loader-manual/metadata---loader-manual-docs-ibmap-remove-mapc-42-8a1.3749cd2adcf3267b2d08.js"
        }
      ]
    },
    "121": {
      "js": [
        {
          "file": "metadata---loader-manual-docs-ibsheet-create-sheet-7-da-c13.4caadb7ab0aa0201b88c.js",
          "hash": "4caadb7ab0aa0201b88c",
          "publicPath": "/loader-manual/metadata---loader-manual-docs-ibsheet-create-sheet-7-da-c13.4caadb7ab0aa0201b88c.js"
        }
      ]
    },
    "122": {
      "js": [
        {
          "file": "metadata---loader-manual-docs-ibsheet-remove-sheetdab-d55.5c95da9d47e6c86c460f.js",
          "hash": "5c95da9d47e6c86c460f",
          "publicPath": "/loader-manual/metadata---loader-manual-docs-ibsheet-remove-sheetdab-d55.5c95da9d47e6c86c460f.js"
        }
      ]
    },
    "123": {
      "js": [
        {
          "file": "metadata---loader-manual-docs-spa-angularca-8-cf5.6f3f527ae0ca3df8f5b2.js",
          "hash": "6f3f527ae0ca3df8f5b2",
          "publicPath": "/loader-manual/metadata---loader-manual-docs-spa-angularca-8-cf5.6f3f527ae0ca3df8f5b2.js"
        }
      ]
    },
    "124": {
      "js": [
        {
          "file": "metadata---loader-manual-docs-spa-reactea-0-4fd.23ee9f52de1c5dc04727.js",
          "hash": "23ee9f52de1c5dc04727",
          "publicPath": "/loader-manual/metadata---loader-manual-docs-spa-reactea-0-4fd.23ee9f52de1c5dc04727.js"
        }
      ]
    },
    "125": {
      "js": [
        {
          "file": "metadata---loader-manual-docs-spa-vue-89-d-adc.f6ce7a3ad19038c817cf.js",
          "hash": "f6ce7a3ad19038c817cf",
          "publicPath": "/loader-manual/metadata---loader-manual-docs-spa-vue-89-d-adc.f6ce7a3ad19038c817cf.js"
        }
      ]
    },
    "126": {
      "js": [
        {
          "file": "metadata---loader-manual-home-featuresfb-3-b24.4f764e4589b03f37c554.js",
          "hash": "4f764e4589b03f37c554",
          "publicPath": "/loader-manual/metadata---loader-manual-home-featuresfb-3-b24.4f764e4589b03f37c554.js"
        }
      ]
    },
    "127": {
      "js": [
        {
          "file": "metadata---loader-manual-home-header-7-f-0-cbb.35ad92c7fb34ec762f21.js",
          "hash": "35ad92c7fb34ec762f21",
          "publicPath": "/loader-manual/metadata---loader-manual-home-header-7-f-0-cbb.35ad92c7fb34ec762f21.js"
        }
      ]
    },
    "128": {
      "js": [
        {
          "file": "nextItem---loader-manual-blog-release-1-1-14-edf-cf7.324bd3148909153823a2.js",
          "hash": "324bd3148909153823a2",
          "publicPath": "/loader-manual/nextItem---loader-manual-blog-release-1-1-14-edf-cf7.324bd3148909153823a2.js"
        }
      ]
    },
    "129": {
      "js": [
        {
          "file": "nextItem---loader-manual-blog-release-1-1-1509-d-4fd.49cbe3c63793e7a2f314.js",
          "hash": "49cbe3c63793e7a2f314",
          "publicPath": "/loader-manual/nextItem---loader-manual-blog-release-1-1-1509-d-4fd.49cbe3c63793e7a2f314.js"
        }
      ]
    },
    "130": {
      "js": [
        {
          "file": "nextItem---loader-manual-blog-release-1-1-166-a-2-850.4515909d1daaff3da05d.js",
          "hash": "4515909d1daaff3da05d",
          "publicPath": "/loader-manual/nextItem---loader-manual-blog-release-1-1-166-a-2-850.4515909d1daaff3da05d.js"
        }
      ]
    },
    "131": {
      "js": [
        {
          "file": "nextItem---loader-manual-blog-release-1-1-18466-993.52f4b34690dcdc9c2fa4.js",
          "hash": "52f4b34690dcdc9c2fa4",
          "publicPath": "/loader-manual/nextItem---loader-manual-blog-release-1-1-18466-993.52f4b34690dcdc9c2fa4.js"
        }
      ]
    },
    "132": {
      "js": [
        {
          "file": "nextItem---loader-manual-blog-release-1-1-19-d-3-f-c86.da867b06380d27efc2d5.js",
          "hash": "da867b06380d27efc2d5",
          "publicPath": "/loader-manual/nextItem---loader-manual-blog-release-1-1-19-d-3-f-c86.da867b06380d27efc2d5.js"
        }
      ]
    },
    "133": {
      "js": [
        {
          "file": "nextItem---loader-manual-blog-release-1-1-21-d-2-a-2f5.e6a7880120bd1eb25000.js",
          "hash": "e6a7880120bd1eb25000",
          "publicPath": "/loader-manual/nextItem---loader-manual-blog-release-1-1-21-d-2-a-2f5.e6a7880120bd1eb25000.js"
        }
      ]
    },
    "134": {
      "js": [
        {
          "file": "nextItem---loader-manual-blog-release-1-1-221-c-3-b9b.ecd201f93fb9ceb46de9.js",
          "hash": "ecd201f93fb9ceb46de9",
          "publicPath": "/loader-manual/nextItem---loader-manual-blog-release-1-1-221-c-3-b9b.ecd201f93fb9ceb46de9.js"
        }
      ]
    },
    "135": {
      "js": [
        {
          "file": "nextItem---loader-manual-blog-release-1-1-237-b-7-127.58ff6a4a1edeb3a95c4e.js",
          "hash": "58ff6a4a1edeb3a95c4e",
          "publicPath": "/loader-manual/nextItem---loader-manual-blog-release-1-1-237-b-7-127.58ff6a4a1edeb3a95c4e.js"
        }
      ]
    },
    "136": {
      "js": [
        {
          "file": "nextItem---loader-manual-blog-release-1-1-242-dd-5f4.2df4f7d42364e7234ef7.js",
          "hash": "2df4f7d42364e7234ef7",
          "publicPath": "/loader-manual/nextItem---loader-manual-blog-release-1-1-242-dd-5f4.2df4f7d42364e7234ef7.js"
        }
      ]
    },
    "137": {
      "js": [
        {
          "file": "nextItem---loader-manual-blog-release-1-1-25011-046.c4386f77204ce29c6208.js",
          "hash": "c4386f77204ce29c6208",
          "publicPath": "/loader-manual/nextItem---loader-manual-blog-release-1-1-25011-046.c4386f77204ce29c6208.js"
        }
      ]
    },
    "138": {
      "js": [
        {
          "file": "nextItem---loader-manual-blog-release-1-2-03-bb-f21.404a178063c997402b11.js",
          "hash": "404a178063c997402b11",
          "publicPath": "/loader-manual/nextItem---loader-manual-blog-release-1-2-03-bb-f21.404a178063c997402b11.js"
        }
      ]
    },
    "139": {
      "js": [
        {
          "file": "nextItem---loader-manual-blog-release-1-3-0-a-8-a-101.4313ee631ee9d9be4672.js",
          "hash": "4313ee631ee9d9be4672",
          "publicPath": "/loader-manual/nextItem---loader-manual-blog-release-1-3-0-a-8-a-101.4313ee631ee9d9be4672.js"
        }
      ]
    },
    "140": {
      "js": [
        {
          "file": "nextItem---loader-manual-blog-release-1-3-147-a-eb9.f3629c2a626b194aead0.js",
          "hash": "f3629c2a626b194aead0",
          "publicPath": "/loader-manual/nextItem---loader-manual-blog-release-1-3-147-a-eb9.f3629c2a626b194aead0.js"
        }
      ]
    },
    "141": {
      "js": [
        {
          "file": "nextItem---loader-manual-blog-release-1-3-2-fd-7-937.077eb8397ae5874fe989.js",
          "hash": "077eb8397ae5874fe989",
          "publicPath": "/loader-manual/nextItem---loader-manual-blog-release-1-3-2-fd-7-937.077eb8397ae5874fe989.js"
        }
      ]
    },
    "142": {
      "js": [
        {
          "file": "nextItem---loader-manual-blog-release-1-3-3-f-51-f61.06e1554ba37c86564d53.js",
          "hash": "06e1554ba37c86564d53",
          "publicPath": "/loader-manual/nextItem---loader-manual-blog-release-1-3-3-f-51-f61.06e1554ba37c86564d53.js"
        }
      ]
    },
    "143": {
      "js": [
        {
          "file": "runtime~main.3b2adf90f49458bbbe6c.js",
          "hash": "3b2adf90f49458bbbe6c",
          "publicPath": "/loader-manual/runtime~main.3b2adf90f49458bbbe6c.js"
        }
      ]
    },
    "144": {
      "js": [
        {
          "file": "tags---loader-manual-blog-tags-947-eda.7bdac772e6710785d00d.js",
          "hash": "7bdac772e6710785d00d",
          "publicPath": "/loader-manual/tags---loader-manual-blog-tags-947-eda.7bdac772e6710785d00d.js"
        }
      ]
    },
    "145": {
      "js": [
        {
          "file": "145.86c4c64b35649d522963.js",
          "hash": "86c4c64b35649d522963",
          "publicPath": "/loader-manual/145.86c4c64b35649d522963.js"
        }
      ]
    },
    "146": {
      "js": [
        {
          "file": "146.b727a11ff3cda56c7560.js",
          "hash": "b727a11ff3cda56c7560",
          "publicPath": "/loader-manual/146.b727a11ff3cda56c7560.js"
        }
      ]
    }
  }
}